{
	"configurations" : 
	[
		{
			"directories" : 
			[
				{
					"build" : ".",
					"jsonFile" : "directory-.-Debug-d0094a50bb2071803777.json",
					"projectIndex" : 0,
					"source" : ".",
					"targetIndexes" : 
					[
						0
					]
				}
			],
			"name" : "Debug",
			"projects" : 
			[
				{
					"directoryIndexes" : 
					[
						0
					],
					"name" : "Project",
					"targetIndexes" : 
					[
						0
					]
				}
			],
			"targets" : 
			[
				{
					"directoryIndex" : 0,
					"id" : "CMakeTarget::@6890427a1f51a3e7e1df",
					"jsonFile" : "target-CMakeTarget-Debug-7a690a16c3b88214df48.json",
					"name" : "CMakeTarget",
					"projectIndex" : 0
				}
			]
		}
	],
	"kind" : "codemodel",
	"paths" : 
	{
		"build" : "C:/Users/akirt/source/repos/AlexKirchuk/BSU/Year 2/Operating Systems/Lab1/Lab1 CMake Solution/Lab1 CMake/out/build/x64-Debug",
		"source" : "C:/Users/akirt/source/repos/AlexKirchuk/BSU/Year 2/Operating Systems/Lab1/Lab1 CMake Solution/Lab1 CMake"
	},
	"version" : 
	{
		"major" : 2,
		"minor" : 8
	}
}
